therepy/__init__.py
therepy/here.py
therepy-0.0.1.dist-info/LICENSE
therepy-0.0.1.dist-info/METADATA
therepy-0.0.1.dist-info/WHEEL
therepy-0.0.1.dist-info/top_level.txt
therepy-0.0.1.dist-info/RECORD
