Metadata-Version: 2.1
Name: therepy
Version: 0.0.1
Summary: Therapeutic filepath management for python data projects.
Author-email: Hans Elliott <hanselliott61@gmail.com>
License: MIT License
Project-URL: Homepage, https://github.com/hans-elliott99/therepy
Project-URL: Bug Tracker, https://github.com/hans-elliott99/therepy/issues
Keywords: here,paths
Classifier: Programming Language :: Python :: 3
Classifier: License :: OSI Approved :: MIT License
Classifier: Operating System :: OS Independent
Requires-Python: >=3.0
License-File: LICENSE
Provides-Extra: dev
Requires-Dist: twine (~=4.0.2) ; extra == 'dev'
Requires-Dist: build (~=0.10.0) ; extra == 'dev'
Provides-Extra: test
Requires-Dist: pytest (~=7.3) ; extra == 'test'
